LICENSE
README.md
setup.py
bin/eva4-svc-yolo-detector
eva4_svc_yolo_detector/__init__.py
eva4_svc_yolo_detector.egg-info/PKG-INFO
eva4_svc_yolo_detector.egg-info/SOURCES.txt
eva4_svc_yolo_detector.egg-info/dependency_links.txt
eva4_svc_yolo_detector.egg-info/requires.txt
eva4_svc_yolo_detector.egg-info/top_level.txt