Metadata-Version: 2.1
Name: eva4-svc-yolo-detector
Version: 0.1.0
Summary: EVA ICS v4 YOLO detector service
Home-page: https://github.com/eva-ics/eva4
Author: Bohemia Automation / Altertech
Author-email: div@altertech.com
License: Apache License 2.0
Classifier: Programming Language :: Python :: 3
Classifier: License :: OSI Approved :: MIT License
Classifier: Topic :: Scientific/Engineering :: Artificial Intelligence
License-File: LICENSE
Requires-Dist: evaics>=0.2.35
Requires-Dist: ultralytics>=8.3.0
